minimal_validator/__init__.py
minimal_validator/validate.py
minimal_validator-0.1.9.dist-info/METADATA
minimal_validator-0.1.9.dist-info/RECORD
minimal_validator-0.1.9.dist-info/WHEEL
minimal_validator-0.1.9.dist-info/top_level.txt
