Metadata-Version: 2.1
Name: minimal-validator
Version: 0.1.9
Summary: Minimal validation framework
Home-page: https://github.com/nestedsoftware/minimal_validator
Author: Nested Software
Author-email: 2969361+nestedsoftware@users.noreply.github.com
License: MIT
Keywords: validation
Platform: UNKNOWN
Classifier: Development Status :: 3 - Alpha
Classifier: License :: OSI Approved :: MIT License
Classifier: Programming Language :: Python
Classifier: Topic :: Software Development
Requires-Dist: email-validator
